pogo_core/__init__.py
pogo_core/error.py
pogo_core/migration.py
pogo_core/py.typed
pogo_core/squash.py
pogo_core/types.py
pogo_core/util/__init__.py
pogo_core/util/migrate.py
pogo_core/util/sql.py
pogo_core/util/testing.py
pogo_core/util/topologicalsort.py
pogo_core-0.1.2.dist-info/METADATA
pogo_core-0.1.2.dist-info/WHEEL
pogo_core-0.1.2.dist-info/RECORD
